LICENSE
MANIFEST.in
README.md
pyproject.toml
setup.cfg
setup.py
versioneer.py
/home/runner/work/openpifpaf/openpifpaf/src/openpifpaf/csrc/src/caf_scored.cpp
/home/runner/work/openpifpaf/openpifpaf/src/openpifpaf/csrc/src/cif_hr.cpp
/home/runner/work/openpifpaf/openpifpaf/src/openpifpaf/csrc/src/cif_seeds.cpp
/home/runner/work/openpifpaf/openpifpaf/src/openpifpaf/csrc/src/cifcaf.cpp
/home/runner/work/openpifpaf/openpifpaf/src/openpifpaf/csrc/src/cifdet.cpp
/home/runner/work/openpifpaf/openpifpaf/src/openpifpaf/csrc/src/module.cpp
/home/runner/work/openpifpaf/openpifpaf/src/openpifpaf/csrc/src/nms_keypoints.cpp
/home/runner/work/openpifpaf/openpifpaf/src/openpifpaf/csrc/src/occupancy.cpp
/home/runner/work/openpifpaf/openpifpaf/src/openpifpaf/csrc/src/utils.cpp
docs/LICENSE.AGPL
docs/LICENSE.BOTNET
docs/LICENSE.CLIPCONVNEXT
docs/LICENSE.CONVNEXTV2
docs/LICENSE.EFFNETV2
docs/LICENSE.HRFORMER
docs/LICENSE.SWIN
docs/LICENSE.XCIT
src/openpifpaf/__init__.py
src/openpifpaf/_version.py
src/openpifpaf/annotation.py
src/openpifpaf/benchmark.py
src/openpifpaf/configurable.py
src/openpifpaf/conftest.py
src/openpifpaf/count_ops.py
src/openpifpaf/cpp_extension.py
src/openpifpaf/eval.py
src/openpifpaf/export_coreml.py
src/openpifpaf/export_onnx.py
src/openpifpaf/export_torchscript.py
src/openpifpaf/headmeta.py
src/openpifpaf/logger.py
src/openpifpaf/logs.py
src/openpifpaf/migrate.py
src/openpifpaf/optimize.py
src/openpifpaf/plugin.py
src/openpifpaf/predict.py
src/openpifpaf/predictor.py
src/openpifpaf/profiler.py
src/openpifpaf/signal.py
src/openpifpaf/stream.py
src/openpifpaf/train.py
src/openpifpaf/utils.py
src/openpifpaf/video.py
src/openpifpaf/csrc/include/openpifpaf/openpifpaf.hpp
src/openpifpaf/csrc/include/openpifpaf/utils.hpp
src/openpifpaf/csrc/include/openpifpaf/decoder/cifcaf.hpp
src/openpifpaf/csrc/include/openpifpaf/decoder/cifdet.hpp
src/openpifpaf/csrc/include/openpifpaf/decoder/utils/caf_scored.hpp
src/openpifpaf/csrc/include/openpifpaf/decoder/utils/cif_hr.hpp
src/openpifpaf_vita.egg-info/PKG-INFO
src/openpifpaf_vita.egg-info/SOURCES.txt
src/openpifpaf_vita.egg-info/dependency_links.txt
src/openpifpaf_vita.egg-info/not-zip-safe
src/openpifpaf_vita.egg-info/requires.txt
src/openpifpaf_vita.egg-info/top_level.txt
