Metadata-Version: 2.1
Name: openpifpaf-vita
Version: 0.14.2
Summary: PifPaf: Composite Fields for Pose Estimation
Home-page: https://github.com/vita-epfl/openpifpaf
Author: EPFL VITA
Author-email: epfl.vita@gmail.com
License: GNU AGPLv3
Requires-Python: >=3.7
Provides-Extra: backbones
Provides-Extra: dev
Provides-Extra: onnx
Provides-Extra: coreml
Provides-Extra: test
Provides-Extra: train
License-File: LICENSE
